pyscreenrecorder/__init__.py
pyscreenrecorder/__version__.py
pyscreenrecorder/pyscreenrecorder.py
pyscreenrecorder-0.0.3.dist-info/LICENSE
pyscreenrecorder-0.0.3.dist-info/METADATA
pyscreenrecorder-0.0.3.dist-info/WHEEL
pyscreenrecorder-0.0.3.dist-info/top_level.txt
pyscreenrecorder-0.0.3.dist-info/RECORD
