Metadata-Version: 2.2
Name: pyscreenrecorder
Version: 0.0.3
Summary: A python package for screen recording with customizable resolution, FPS, and mouse tracking.
Home-page: https://github.com/SSujitX/pyscreenrecorder
Author: Sujit Biswas
Author-email: ssujitxx@gmail.com
License: MIT
Project-URL: Bug Tracker, https://github.com/SSujitX/pyscreenrecorder/issues
Project-URL: Documentation, https://github.com/SSujitX/pyscreenrecorder#readme
Project-URL: Source Code, https://github.com/SSujitX/pyscreenrecorder
Keywords: screen recorder,screen capture,video recording,screen recording,recording,screenshots,mouse tracking,automated screen recording
Classifier: Development Status :: 4 - Beta
Classifier: Intended Audience :: Developers
Classifier: Topic :: Multimedia :: Video
Classifier: Programming Language :: Python :: 3
Classifier: License :: OSI Approved :: MIT License
Classifier: Operating System :: OS Independent
Requires-Python: >=3.9
License-File: LICENSE
Requires-Dist: mss==10.0.0
Requires-Dist: numpy==2.2.2
Requires-Dist: opencv-python==4.11.0.86
Requires-Dist: PyAutoGUI==0.9.54
Dynamic: author
Dynamic: author-email
Dynamic: classifier
Dynamic: description
Dynamic: description-content-type
Dynamic: home-page
Dynamic: keywords
Dynamic: license
Dynamic: project-url
Dynamic: requires-dist
Dynamic: requires-python
Dynamic: summary
